MANIFEST.in
README.md
setup.py
hexfile/__init__.py
hexfile/core.py
hexfile.egg-info/PKG-INFO
hexfile.egg-info/SOURCES.txt
hexfile.egg-info/dependency_links.txt
hexfile.egg-info/top_level.txt