Metadata-Version: 1.0
Name: hexfile
Version: 0.0.1
Summary: Library for loading and manipulating hex files.
Home-page: http://www.github.com/ryansturmer/hexfile
Author: Ryan Sturmer
Author-email: ryansturmer@gmail.com
License: UNKNOWN
Platform: UNKNOWN
